{
  "cakes": [
    { "id": 1, "category": "cakes", "name": "Fruit Cake", "price": 800, "rating": 4.4, "weight": 1, "image": "images/Fruit Cake.jpg", "description": "A delicious flavorful fruit cake topped with fresh seasonal fruits. A perfect choice for every occasion." },
    { "id": 2, "category": "cheese cakes", "name": "Classic Cheesecake", "price": 1250, "rating": 4.2, "weight": 1, "image": "images/Classic Cheesecake.jpg", "description": "The perfect cheesecake for Fall! Swirled with pumpkin flavor and a buttery graham cracker crust." },
    { "id": 3, "category": "cakes", "name": "Monster Theme Cake", "price": 550, "rating": 4.3, "weight": 0.5, "image": "images/Monster Theme Cake.jpg", "description": "A fondant-type Cookies Monster Cake — an excellent choice for any game lover." },
    { "id": 4, "category": "cup cakes", "name": "Pumpkin Spice Cupcakes-6", "price": 360, "rating": 4.5, "weight": 0.6, "image": "images/Pumpkin Spice Cupcakes.jpg", "description": "Hearty pumpkin cupcakes topped with cinnamon cream cheese frosting." },
    { "id": 5, "category": "cookies", "name": "Cookies Cream Cake", "price": 1000, "rating": 4.7, "weight": 1, "image": "images/Cookies Cream Cake.jpg", "description": "Soft and buttery white cake with plenty of sweet Oreo cookies. Fun and simple for a crowd!" },
    { "id": 6, "category": "cup cakes", "name": "Easter Cupcakes-6", "price": 300, "rating": 4.1, "weight": 0.6, "image": "images/Easter Cupcakes.jpg", "description": "Moist chocolate cupcake base with coconut buttercream frosting and Easter egg candies on top." },
    { "id": 7, "category": "chocolates", "name": "Chocolate Summer Berries", "price": 1100, "rating": 4.3, "weight": 0.5, "image": "images/Chocolate Summer Berries.jpg", "description": "Silky Dark Milk chocolate cake topped with strawberries, blueberries and cherries." },
    { "id": 8, "category": "muffins", "name": "Muffin Devil Horns-3", "price": 375, "rating": 4.9, "weight": 0.45, "image": "images/Muffin Devil Horns.jpg", "description": "Adorable Devil Cupcakes — perfect for birthdays or Halloween celebrations." },
    { "id": 9, "category": "cup cakes", "name": "Berries Summer Cupcakes-6", "price": 420, "rating": 4.2, "weight": 0.6, "image": "images/Berries Summer Cupcakes.jpg", "description": "Moist vanilla cake with whipped almond filling and mixed berry frosting topped with fresh berries." },
    { "id": 10, "category": "brownies", "name": "Brownies Different Flavor-6", "price": 600, "rating": 4.9, "weight": 0.9, "image": "images/Brownies Different Flavor.jpg", "description": "Worldwide-famous cake-like brownies in multiple flavors. Serve with milk or ice cream." },
    { "id": 11, "category": "cheese cakes", "name": "Cherry Jelly Cheesecake", "price": 1300, "rating": 5, "weight": 1, "image": "images/Cherry Jelly Cheesecake.jpg", "description": "No-bake cherry cheesecake — a fresh and tasty way to appreciate this red and juicy fruit." },
    { "id": 12, "category": "cakes", "name": "Chocolate Blueberries Cake", "price": 2000, "rating": 4.8, "weight": 1.5, "image": "images/Chocolate Blueberries Cake.jpg", "description": "Rich chocolate cake layered with fresh blueberries and whipped cream frosting." },
    { "id": 13, "category": "cup cakes", "name": "Chocolate Cupcake-4", "price": 400, "rating": 4.5, "weight": 0.4, "image": "images/Chocolate Cupcake.jpg", "description": "Super moist chocolate cupcakes bursting with rich chocolaty flavor. Easy to make and perfect for parties." },
    { "id": 14, "category": "brownies", "name": "Isometric Chocolate Brownies-3", "price": 330, "rating": 4.7, "weight": 0.3, "image": "images/Isometric chocolate brownies.jpg", "description": "Traditional brownies with nuts and cocoa frosting. Classic chocolate fudge brownie." },
    { "id": 15, "category": "muffins", "name": "Muffin Ghost-2", "price": 250, "rating": 4.9, "weight": 0.3, "image": "images/Muffin Ghost.jpg", "description": "Ghostly Halloween cupcakes — a cleverly disguised arrangement of spooky muffins." },
    { "id": 16, "category": "cookies", "name": "Butter Cookies", "price": 450, "rating": 5, "weight": 0.5, "image": "images/Butter Cookies.jpg", "description": "Crisp, delicious butter cookies with amazing butter flavor and a melt-in-your-mouth consistency." },
    { "id": 17, "category": "chocolates", "name": "Chocolate Bonbons-500gm", "price": 800, "rating": 4.9, "weight": 0.5, "image": "images/Chocolate Bonbons.jpg", "description": "Beautiful chocolate bonbons made with tempered dark chocolate and milk chocolate ganache filling." },
    { "id": 18, "category": "cookies", "name": "Chocolate Cookies-500gm", "price": 600, "rating": 5, "weight": 0.5, "image": "images/Chocolate Cookies.jpg", "description": "Classic chocolate chip cookies with rich chocolate morsels baked to golden perfection." },
    { "id": 19, "category": "cakes", "name": "Vanilla Dream Cake", "price": 950, "rating": 4.6, "weight": 1, "image": "images/Fruit Cake.jpg", "description": "Light and fluffy vanilla sponge cake layered with fresh cream and seasonal fruits." },
    { "id": 20, "category": "cakes", "name": "Red Velvet Cake", "price": 1200, "rating": 4.8, "weight": 1, "image": "images/Chocolate Blueberries Cake.jpg", "description": "Classic red velvet cake with cream cheese frosting — a timeless crowd-pleaser." },
    { "id": 21, "category": "cakes", "name": "Black Forest Cake", "price": 1100, "rating": 4.7, "weight": 1, "image": "images/Monster Theme Cake.jpg", "description": "Layers of chocolate sponge, whipped cream and cherries in this German classic." },
    { "id": 22, "category": "cakes", "name": "Butterscotch Cake", "price": 850, "rating": 4.4, "weight": 1, "image": "images/Cookies Cream Cake.jpg", "description": "Moist butterscotch cake topped with caramel drizzle and crunchy praline bits." },
    { "id": 23, "category": "cakes", "name": "Pineapple Cake", "price": 750, "rating": 4.3, "weight": 1, "image": "images/Fruit Cake.jpg", "description": "Soft pineapple sponge cake with pineapple cream frosting and fresh pineapple chunks." },
    { "id": 24, "category": "cakes", "name": "Strawberry Delight Cake", "price": 1050, "rating": 4.6, "weight": 1, "image": "images/Chocolate Blueberries Cake.jpg", "description": "Fresh strawberry cake with strawberry compote filling and whipped cream frosting." },
    { "id": 25, "category": "cheese cakes", "name": "Blueberry Cheesecake", "price": 1400, "rating": 4.7, "weight": 1, "image": "images/Cherry Jelly Cheesecake.jpg", "description": "Creamy New York style cheesecake topped with a luscious blueberry compote." },
    { "id": 26, "category": "cheese cakes", "name": "Mango Cheesecake", "price": 1350, "rating": 4.8, "weight": 1, "image": "images/Classic Cheesecake.jpg", "description": "No-bake mango cheesecake with a buttery biscuit base and fresh mango topping." },
    { "id": 27, "category": "cheese cakes", "name": "Oreo Cheesecake", "price": 1450, "rating": 4.9, "weight": 1, "image": "images/Cherry Jelly Cheesecake.jpg", "description": "Rich and creamy Oreo cheesecake with crushed Oreo crust and Oreo cream filling." },
    { "id": 28, "category": "cheese cakes", "name": "Lemon Cheesecake", "price": 1200, "rating": 4.5, "weight": 1, "image": "images/Classic Cheesecake.jpg", "description": "Tangy lemon cheesecake with a zesty lemon curd topping on a buttery graham cracker base." },
    { "id": 29, "category": "cup cakes", "name": "Red Velvet Cupcakes-6", "price": 480, "rating": 4.7, "weight": 0.6, "image": "images/Chocolate Cupcake.jpg", "description": "Mini red velvet cupcakes with cream cheese frosting — perfect for parties and gifting." },
    { "id": 30, "category": "cup cakes", "name": "Vanilla Cupcakes-6", "price": 320, "rating": 4.4, "weight": 0.6, "image": "images/Easter Cupcakes.jpg", "description": "Classic vanilla cupcakes with fluffy buttercream frosting in assorted pastel colors." },
    { "id": 31, "category": "cup cakes", "name": "Lemon Cupcakes-6", "price": 350, "rating": 4.3, "weight": 0.6, "image": "images/Berries Summer Cupcakes.jpg", "description": "Zesty lemon cupcakes with lemon buttercream frosting and a candied lemon slice on top." },
    { "id": 32, "category": "cup cakes", "name": "Caramel Cupcakes-4", "price": 380, "rating": 4.5, "weight": 0.4, "image": "images/Pumpkin Spice Cupcakes.jpg", "description": "Soft caramel cupcakes drizzled with salted caramel sauce and topped with caramel buttercream." },
    { "id": 33, "category": "cup cakes", "name": "Funfetti Cupcakes-6", "price": 360, "rating": 4.6, "weight": 0.6, "image": "images/Easter Cupcakes.jpg", "description": "Colorful funfetti cupcakes loaded with rainbow sprinkles inside and out — kids love them!" },
    { "id": 34, "category": "brownies", "name": "Walnut Brownies-6", "price": 550, "rating": 4.8, "weight": 0.6, "image": "images/Brownies Different Flavor.jpg", "description": "Fudgy chocolate brownies loaded with crunchy walnuts — the ultimate indulgence." },
    { "id": 35, "category": "brownies", "name": "Caramel Swirl Brownies-4", "price": 480, "rating": 4.7, "weight": 0.4, "image": "images/Isometric chocolate brownies.jpg", "description": "Rich chocolate brownies with a gorgeous caramel swirl baked right in." },
    { "id": 36, "category": "brownies", "name": "Peanut Butter Brownies-4", "price": 520, "rating": 4.9, "weight": 0.4, "image": "images/Brownies Different Flavor.jpg", "description": "Decadent chocolate brownies swirled with creamy peanut butter for the ultimate combo." },
    { "id": 37, "category": "brownies", "name": "Oreo Brownies-6", "price": 580, "rating": 4.8, "weight": 0.6, "image": "images/Isometric chocolate brownies.jpg", "description": "Fudgy brownies topped with whole Oreo cookies pressed into the batter before baking." },
    { "id": 38, "category": "muffins", "name": "Blueberry Muffins-4", "price": 320, "rating": 4.6, "weight": 0.4, "image": "images/Muffin Ghost.jpg", "description": "Classic bakery-style blueberry muffins bursting with fresh blueberries and a crunchy sugar top." },
    { "id": 39, "category": "muffins", "name": "Banana Walnut Muffins-4", "price": 300, "rating": 4.5, "weight": 0.4, "image": "images/Muffin Devil Horns.jpg", "description": "Moist banana muffins packed with crunchy walnuts — a perfect breakfast treat." },
    { "id": 40, "category": "muffins", "name": "Chocolate Chip Muffins-4", "price": 340, "rating": 4.7, "weight": 0.4, "image": "images/Muffin Ghost.jpg", "description": "Soft and fluffy muffins loaded with chocolate chips — a chocolate lover's dream." },
    { "id": 41, "category": "muffins", "name": "Lemon Poppy Seed Muffins-4", "price": 310, "rating": 4.4, "weight": 0.4, "image": "images/Muffin Devil Horns.jpg", "description": "Bright and zesty lemon muffins with poppy seeds and a sweet lemon glaze drizzle." },
    { "id": 42, "category": "muffins", "name": "Cinnamon Streusel Muffins-4", "price": 330, "rating": 4.6, "weight": 0.4, "image": "images/Muffin Ghost.jpg", "description": "Warm cinnamon muffins topped with a buttery streusel crumble — perfect with coffee." },
    { "id": 43, "category": "cookies", "name": "Oatmeal Raisin Cookies-500gm", "price": 420, "rating": 4.5, "weight": 0.5, "image": "images/Butter Cookies.jpg", "description": "Chewy oatmeal cookies packed with plump raisins and a hint of cinnamon spice." },
    { "id": 44, "category": "cookies", "name": "Snickerdoodle Cookies-500gm", "price": 400, "rating": 4.6, "weight": 0.5, "image": "images/Chocolate Cookies.jpg", "description": "Soft and chewy cinnamon sugar cookies with a crinkly top — a classic American favorite." },
    { "id": 45, "category": "cookies", "name": "Peanut Butter Cookies-500gm", "price": 450, "rating": 4.7, "weight": 0.5, "image": "images/Butter Cookies.jpg", "description": "Rich and crumbly peanut butter cookies with a classic fork-pressed pattern on top." },
    { "id": 46, "category": "cookies", "name": "Sugar Cookies-500gm", "price": 380, "rating": 4.4, "weight": 0.5, "image": "images/Chocolate Cookies.jpg", "description": "Soft and thick sugar cookies with a sweet vanilla glaze and colorful sprinkles." },
    { "id": 47, "category": "chocolates", "name": "Dark Chocolate Truffles-250gm", "price": 650, "rating": 4.8, "weight": 0.25, "image": "images/Chocolate Bonbons.jpg", "description": "Handcrafted dark chocolate truffles dusted with cocoa powder — intensely rich and smooth." },
    { "id": 48, "category": "chocolates", "name": "White Chocolate Bark-200gm", "price": 550, "rating": 4.5, "weight": 0.2, "image": "images/Chocolate Summer Berries.jpg", "description": "Creamy white chocolate bark topped with dried cranberries, pistachios and sea salt." },
    { "id": 49, "category": "chocolates", "name": "Milk Chocolate Fudge-300gm", "price": 700, "rating": 4.7, "weight": 0.3, "image": "images/Chocolate Bonbons.jpg", "description": "Smooth and creamy milk chocolate fudge cut into bite-sized squares — melt-in-mouth goodness." },
    { "id": 50, "category": "chocolates", "name": "Hazelnut Pralines-250gm", "price": 900, "rating": 4.9, "weight": 0.25, "image": "images/Chocolate Summer Berries.jpg", "description": "Belgian-style hazelnut pralines with a crunchy hazelnut center coated in dark chocolate." },
    { "id": 51, "category": "cakes", "name": "Carrot Cake", "price": 900, "rating": 4.5, "weight": 1, "image": "images/Fruit Cake.jpg", "description": "Moist spiced carrot cake with cream cheese frosting and candied walnut decoration." },
    { "id": 52, "category": "cakes", "name": "Coconut Cake", "price": 950, "rating": 4.4, "weight": 1, "image": "images/Cookies Cream Cake.jpg", "description": "Light coconut sponge cake layered with coconut cream and toasted coconut flakes." },
    { "id": 53, "category": "cheese cakes", "name": "Strawberry Cheesecake", "price": 1350, "rating": 4.8, "weight": 1, "image": "images/Cherry Jelly Cheesecake.jpg", "description": "Creamy cheesecake topped with a vibrant fresh strawberry glaze and whole strawberries." },
    { "id": 54, "category": "brownies", "name": "S'mores Brownies-4", "price": 500, "rating": 4.8, "weight": 0.4, "image": "images/Brownies Different Flavor.jpg", "description": "Fudgy brownies layered with graham crackers, marshmallows and toasted to perfection." }
  ]
}
